README.txt
setup.py
PyHacc.egg-info/PKG-INFO
PyHacc.egg-info/SOURCES.txt
PyHacc.egg-info/dependency_links.txt
PyHacc.egg-info/requires.txt
PyHacc.egg-info/top_level.txt
pyhacc/BalanceDock.py
pyhacc/DateDock.py
pyhacc/PyHaccLib.py
pyhacc/PyHaccMainWindow.py
pyhacc/PyHaccSchema.py
pyhacc/PyHaccUI.py
pyhacc/__init__.py
pyhacc/accounts.py
pyhacc/accounttypes.py
pyhacc/icons_rc.py
pyhacc/journals.py
pyhacc/reports.py
pyhacc/tags.py
pyhacc/transactions.py
pyhacc/http/__init__.py
pyhacc/http/__main__.py
pyhacc/http/serve.py
scripts/pyhacc
scripts/pyhaccgui
scripts/qhacc2pyhacc.py