Metadata-Version: 1.1
Name: PyHacc
Version: 0.9.0
Summary: pyhacc personal accounting
Home-page: https://bitbucket.org/jbmohler/pyhacc/
Author: Joel B. Mohler
Author-email: joel@kiwistrawberry.us
License: GPLv2+
Platform: UNKNOWN
Classifier: Development Status :: 4 - Beta
Classifier: Intended Audience :: End Users/Desktop
Classifier: Topic :: Office/Business :: Financial :: Accounting
Classifier: License :: OSI Approved :: GNU General Public License (GPL)
Classifier: Programming Language :: Python :: 2
Classifier: Programming Language :: Python :: 3
Classifier: Topic :: Database :: Front-Ends
Classifier: Operating System :: OS Independent
Classifier: Environment :: Win32 (MS Windows)
Classifier: Environment :: X11 Applications :: Qt
